[
    {
        "product":"keyboard",
        "id":"kb1",
        "name" : "60% Black",
        "numKeys":61,
        "color": "Black",
        "pic":"img/keyboards/60.png"
    },
    {
        "product":"keyboard",
        "id":"kb2",
        "name" : "65% Black",
        "numKeys": 70,
        "color": "Black",
        "pic":"img/keyboards/65.png"
    },
    {
        "product":"keyboard",
        "id":"kb3",
        "name" : "80% Black",
        "numKeys": 87,
        "color": "Black",
        "pic":"img/keyboards/87.png"
    },
    {
        "product":"keyboard",
        "id":"kb4",
        "name" : "100% Black",
        "numKeys":104,
        "color": "Black",
        "pic":"img/keyboards/104.png"
    },
    {
        "product":"keyboard",
        "id":"kb5",
        "name" : "60% White",
        "numKeys":61,
        "color": "White",
        "pic":"img/keyboards/60White.png"
    },
    {
        "product":"keyboard",
        "id":"kb6",
        "name" : "60% Mint",
        "numKeys":61,
        "color": "Mint",
        "pic":"img/keyboards/60Mint.png"
    },
    {
        "product":"keyboard",
        "id":"kb7",
        "name" : "65% Red",
        "numKeys":70,
        "color": "Red",
        "pic":"img/keyboards/65Red-PigEdition.png"
    },
    {
        "product":"keyboard",
        "id":"kb8",
        "name" : "80% Grey",
        "numKeys":87,
        "color": "Grey",
        "pic":"img/keyboards/80Grey.png"
    },
    {
        "product":"keyboard",
        "id":"kb9",
        "name" : "100% Brown",
        "numKeys":104,
        "color": "Brown",
        "pic":"img/keyboards/100Brown.png"
    },
    {
        "product":"keyboard",
        "id":"kb10",
        "name" : "100% Grey",
        "numKeys":104,
        "color": "Grey",
        "pic":"img/keyboards/100Grey.png"
    },
    {
        "product":"keyboard",
        "id":"kb11",
        "name" : "100% Pink",
        "numKeys":104,
        "color": "Pink",
        "pic":"img/keyboards/100Pink.png"
    },
    {
        "product":"keyboard",
        "id":"kb12",
        "name" : "100% White",
        "numKeys":104,
        "color": "White",
        "pic":"img/keyboards/100White.png"
    },
    {
        "product":"keyboard",
        "id":"kb13",
        "name" : "100% Yellow",
        "numKeys":104,
        "color": "Yellow",
        "pic":"img/keyboards/100Yellow.png"
    },
    {
        "product":"keyboard",
        "id":"kb14",
        "name" : "75% Black",
        "numKeys":82,
        "color": "Black",
        "pic":"img/keyboards/75.png"
    },
    {
        "product":"keyboard",
        "id":"kb15",
        "name" : "75% White",
        "numKeys":82,
        "color": "White",
        "pic":"img/keyboards/75White.jpg"
     }
]